{"current_node":{"node_id":9,"value":{"turn":10,"piece":"bM","position":"bA1\\"},"parent":8},"tree":{"name":"analysis","nodes":[{"node_id":0,"value":{"turn":1,"piece":"wL","position":""},"parent":null},{"node_id":1,"value":{"turn":2,"piece":"bL","position":"wL-"},"parent":0},{"node_id":2,"value":{"turn":3,"piece":"wQ","position":"\\wL"},"parent":1},{"node_id":3,"value":{"turn":4,"piece":"bQ","position":"bL\\"},"parent":2},{"node_id":4,"value":{"turn":5,"piece":"wM","position":"/wQ"},"parent":3},{"node_id":5,"value":{"turn":6,"piece":"bA1","position":"bL/"},"parent":4},{"node_id":6,"value":{"turn":7,"piece":"wS1","position":"wM\\"},"parent":5},{"node_id":7,"value":{"turn":8,"piece":"bG1","position":"\\bA1"},"parent":6},{"node_id":8,"value":{"turn":9,"piece":"wP","position":"wS1\\"},"parent":7},{"node_id":9,"value":{"turn":10,"piece":"bM","position":"bA1\\"},"parent":8}]},"hashes":{"1223344268319051727":9,"9933636654818954579":0,"3134152141365092189":1,"934990754504361350":7,"2610006682021829421":4,"6500033481364485245":3,"4087768731940900806":6,"11009839842100312898":8,"9156159496771112829":5,"3675894809633074368":2},"game_type":"MLP"}